ee_s1_ard/__init__.py
ee_s1_ard/border_noise_correction.py
ee_s1_ard/helper.py
ee_s1_ard/speckle_filter.py
ee_s1_ard/terrain_flattening.py
ee_s1_ard/wrapper.py
ee_s1_ard-1.0.4.dist-info/METADATA
ee_s1_ard-1.0.4.dist-info/WHEEL
ee_s1_ard-1.0.4.dist-info/licenses/LICENSE
ee_s1_ard-1.0.4.dist-info/RECORD
