Metadata-Version: 2.4
Name: ee_s1_ard
Version: 1.0.4
Summary: Sentinel 1 Analysis Ready Data for GEE.
Project-URL: Homepage, https://mateuspinto.github.io/ee-s1-ard/
Project-URL: Repository, https://github.com/mateuspinto/ee-s1-ard
Project-URL: Documentation, https://mateuspinto.github.io/ee-s1-ard/
Author-email: Mateus Pinto da Silva <mateuspinto@gmail.com>
License-File: LICENSE
Keywords: python
Classifier: Intended Audience :: Developers
Classifier: Programming Language :: Python
Classifier: Programming Language :: Python :: 3.11
Classifier: Programming Language :: Python :: 3.12
Classifier: Programming Language :: Python :: 3.13
Classifier: Topic :: Software Development :: Libraries :: Python Modules
Requires-Python: <4.0,>=3.11
Requires-Dist: earthengine-api>=1.5.7
